{
  "created": 1781496267,
  "usage": {
    "input_tokens": 79,
    "output_tokens": 6500,
    "total_tokens": 6579,
    "input_tokens_details": {
      "text_tokens": 79,
      "image_tokens": 0,
      "cached_tokens": 0
    },
    "output_tokens_details": {
      "text_tokens": 0,
      "image_tokens": 6500,
      "reasoning_tokens": 0
    }
  },
  "revised_prompt": "A clean premium product render of modern office blue-light glasses as a generic relic icon, centered single object, gray-blue frame, cold white reflections on the lenses, high contrast, crisp commercial 2D game icon style, readable at small UI size, isolated on plain light neutral background, no text, no label, no logo, no watermark, no character, no busy scene, no border.",
  "url": "https://image.nianhua.store/images/2026/06/15/1781496294_2fc1a9de47cc26173e396343f75d814b.png"
}
